pystack/__init__.py
pystack/__main__.py
pystack/_pystack.cpython-38-aarch64-linux-gnu.so
pystack/_pystack.pyi
pystack/_version.py
pystack/colors.py
pystack/engine.py
pystack/errors.py
pystack/maps.py
pystack/process.py
pystack/py.typed
pystack/traceback_formatter.py
pystack/types.py
pystack.libs/libdw-0-2654aa0b.193.so
pystack.libs/libelf-0-0cc3820e.193.so
pystack.libs/libzstd-28866717.so.1.4.4
pystack-1.6.0.dist-info/LICENSE
pystack-1.6.0.dist-info/METADATA
pystack-1.6.0.dist-info/WHEEL
pystack-1.6.0.dist-info/entry_points.txt
pystack-1.6.0.dist-info/top_level.txt
pystack-1.6.0.dist-info/RECORD
pystack-1.6.0.dist-info/sboms/auditwheel.cdx.json
